hts_tst_mcp_demo/__init__.py
hts_tst_mcp_demo-0.1.3.dist-info/WHEEL
hts_tst_mcp_demo-0.1.3.dist-info/entry_points.txt
hts_tst_mcp_demo-0.1.3.dist-info/METADATA
hts_tst_mcp_demo-0.1.3.dist-info/RECORD
